diffused/__init__.py
diffused/differ.py
diffused/scanners/__init__.py
diffused/scanners/acs.py
diffused/scanners/base.py
diffused/scanners/models.py
diffused/scanners/trivy.py
diffused_lib-0.3.0.dist-info/METADATA
diffused_lib-0.3.0.dist-info/WHEEL
diffused_lib-0.3.0.dist-info/RECORD
