Metadata-Version: 2.4
Name: diffused-lib
Version: 0.3.0
Summary: A vulnerability scan diffing library for container images and SBOMs
Project-URL: documentation, https://github.com/konflux-ci/diffused/tree/main/docs
Project-URL: repository, https://github.com/konflux-ci/diffused
Project-URL: homepage, https://github.com/konflux-ci/diffused
Author: Willian Rampazzo
Author-email: willianr@redhat.com
License-Expression: Apache-2.0
Keywords: container,scanning,security,vulnerability
Classifier: Development Status :: 3 - Alpha
Classifier: Environment :: Console
Classifier: Intended Audience :: Developers
Classifier: Intended Audience :: System Administrators
Classifier: License :: OSI Approved :: Apache Software License
Classifier: Programming Language :: Python :: 3
Classifier: Programming Language :: Python :: 3.9
Classifier: Programming Language :: Python :: 3.10
Classifier: Programming Language :: Python :: 3.11
Classifier: Programming Language :: Python :: 3.12
Classifier: Topic :: Security
Classifier: Topic :: System :: Systems Administration
Requires-Python: <4.0,>=3.9
Provides-Extra: black
Requires-Dist: black; extra == 'black'
Provides-Extra: dev
Requires-Dist: diffused[black]; extra == 'dev'
Requires-Dist: diffused[flake8]; extra == 'dev'
Requires-Dist: diffused[isort]; extra == 'dev'
Requires-Dist: diffused[mypy]; extra == 'dev'
Requires-Dist: diffused[pytest]; extra == 'dev'
Requires-Dist: tox; extra == 'dev'
Provides-Extra: flake8
Requires-Dist: flake8; extra == 'flake8'
Provides-Extra: isort
Requires-Dist: isort; extra == 'isort'
Provides-Extra: mypy
Requires-Dist: mypy; extra == 'mypy'
Provides-Extra: pytest
Requires-Dist: pytest; extra == 'pytest'
Requires-Dist: pytest-cov; extra == 'pytest'
